meiiiok/__init__.py
meiiiok/main.py
meiiiok-0.1.2.dist-info/METADATA
meiiiok-0.1.2.dist-info/WHEEL
meiiiok-0.1.2.dist-info/top_level.txt
meiiiok-0.1.2.dist-info/RECORD
